redstone/__init__.py
redstone/common/models/test.py
redstone_lib-0.1.2.dist-info/METADATA
redstone_lib-0.1.2.dist-info/WHEEL
redstone_lib-0.1.2.dist-info/RECORD
